shoal_agent/__init__.py
shoal_agent/__version__.py
shoal_agent/config.py
shoal_agent-1.0.2.data/data/share/shoal-agent/shoal-agent.init
shoal_agent-1.0.2.data/data/share/shoal-agent/shoal-agent.logrotate
shoal_agent-1.0.2.data/data/share/shoal-agent/shoal-agent.service
shoal_agent-1.0.2.data/data/share/shoal-agent/shoal_agent.conf
shoal_agent-1.0.2.data/scripts/shoal-agent
shoal_agent-1.0.2.data/scripts/shoal-agent-installation.sh
shoal_agent-1.0.2.dist-info/METADATA
shoal_agent-1.0.2.dist-info/WHEEL
shoal_agent-1.0.2.dist-info/top_level.txt
shoal_agent-1.0.2.dist-info/RECORD
