Metadata-Version: 2.1
Name: shoal-agent
Version: 1.0.2
Summary: A squid cache publishing and advertising tool designed to work in fast changing environments
Home-page: http://github.com/hep-gc/shoal
Author: Mike Chester, Colson Drimiel, Ian Gable, Alex Lam, Rob Prior, Ryan Taylor, Steve Traylen, Marcus Ebert, Da Meng
Author-email: heprc-shoal@uvic.ca
License: 'GPL3' or 'Apache 2'
Platform: UNKNOWN
Requires-Dist: netifaces (>=0.5)
Requires-Dist: pika (>=0.9.5)
Requires-Dist: pystun3 (>=1.0.0)
Requires-Dist: requests (>=2.6.0)
